topsis_102203992/__init__.py
topsis_102203992/topsis_102203992.py
topsis_102203992-1.1.dist-info/METADATA
topsis_102203992-1.1.dist-info/WHEEL
topsis_102203992-1.1.dist-info/license.txt
topsis_102203992-1.1.dist-info/top_level.txt
topsis_102203992-1.1.dist-info/RECORD
