Metadata-Version: 2.2
Name: topsis_102203992
Version: 1.1
Summary: Package for Topsis Score Calculation
Author: Ishita Garg
License-File: license.txt
Requires-Dist: pandas>=1.0.0
Requires-Dist: numpy>=1.18.0
Dynamic: author
Dynamic: description
Dynamic: description-content-type
Dynamic: requires-dist
Dynamic: summary
